{
  "avai": "https://logodetimes.com/times/avai/logo-avai-1024.png",
  "barra": "https://upload.wikimedia.org/wikipedia/pt/9/90/BarraFC2020.png",
  "brusque": "https://logodetimes.com/times/brusque/logo-brusque-1024.png",
  "chapecoense-sc": "https://logodetimes.com/times/chapecoense/logo-chapecoense-1024.png",
  "concordia": "https://upload.wikimedia.org/wikipedia/pt/1/16/Conc%C3%B3rdia_Atl%C3%A9tico_Clube.png",
  "criciuma": "https://logodownload.org/wp-content/uploads/2017/02/Criciuma-logo-escudo.png",
  "figueirense": "https://logodetimes.com/times/figueirense/logo-figueirense-1024.png",
  "hercilio-luz": "https://upload.wikimedia.org/wikipedia/pt/5/5d/Herc%C3%ADlio_Luz-SC.png",
  "internacional-sc": "https://upload.wikimedia.org/wikipedia/commons/thumb/d/d7/Inter-de-lages-escudo.png/800px-Inter-de-lages-escudo.png",
  "joinville": "https://upload.wikimedia.org/wikipedia/pt/3/31/Joinville-SC.png",
  "marcilio-dias": "https://upload.wikimedia.org/wikipedia/pt/3/3f/Clube_N%C3%A1utico_Marc%C3%ADlio_Dias.png?20181220123137",
  "nacao": "https://footballlogosandkits.com/images_esc3/CONM/BRASIL/escudos/ESC_NA%C7%C3O%20ESPORTES.png"
}
